deck_of_cards/__init__.py
deck_of_cards/deck_of_cards.py
deck_of_cards/graphics.py
deck_of_cards/test_deck_of_cards.py
deck_of_cards-0.0.10.dist-info/METADATA
deck_of_cards-0.0.10.dist-info/WHEEL
deck_of_cards-0.0.10.dist-info/top_level.txt
deck_of_cards-0.0.10.dist-info/RECORD
