Metadata-Version: 2.1
Name: deck-of-cards
Version: 0.0.10
Summary: A module to create and interact with a deck of cards object
Home-page: https://github.com/SimonTheChain/deck_of_cards
Author: Simon Lachaîne
Author-email: simonthechain@gmail.com
License: UNKNOWN
Platform: UNKNOWN
Classifier: Programming Language :: Python :: 3
Classifier: License :: OSI Approved :: MIT License
Classifier: Operating System :: OS Independent
